src/__init__.py
src/cli.py
src/doc_crawler.py
src/models/__init__.py
src/models/crawler_stats.py
src/processors/__init__.py
src/processors/html_processor.py
src/utils/__init__.py
src/utils/cli.py
src/utils/config.py
src/utils/logger.py
src/utils/storage.py
src/utils/url_utils.py
tests/__init__.py
tests/test_basic.py
docu_crawler-0.1.1.dist-info/LICENSE
docu_crawler-0.1.1.dist-info/METADATA
docu_crawler-0.1.1.dist-info/WHEEL
docu_crawler-0.1.1.dist-info/entry_points.txt
docu_crawler-0.1.1.dist-info/top_level.txt
docu_crawler-0.1.1.dist-info/RECORD
